{"2024-01-23":{"price":{"open":574.2,"max":618.1,"min":574,"close":610,"prevClose":584.7,"diff":25.299999999999955},"numTrans":1016,"tradedShares":225228,"amount":135525745.9},"2024-01-22":{"price":{"open":595.1,"max":611.8,"min":561,"close":584.7,"prevClose":599.9,"diff":-15.199999999999932},"numTrans":943,"tradedShares":255908,"amount":150141367.5},"2024-01-21":{"price":{"open":617,"max":630,"min":596.2,"close":599.9,"prevClose":625,"diff":-25.100000000000023},"numTrans":911,"tradedShares":231681,"amount":141363540.7},"2024-01-18":{"price":{"open":600,"max":635,"min":586.1,"close":625,"prevClose":608,"diff":17},"numTrans":1025,"tradedShares":206436,"amount":128042535.1},"2024-01-17":{"price":{"open":606,"max":641,"min":604.7,"close":608,"prevClose":594.2,"diff":13.799999999999955},"numTrans":1473,"tradedShares":306433,"amount":189708060.2},"2024-01-16":{"price":{"open":551,"max":594.2,"min":550,"close":594.2,"prevClose":540.2,"diff":54},"numTrans":1208,"tradedShares":362806,"amount":211397478.9},"2024-01-14":{"price":{"open":556,"max":557.7,"min":538,"close":540.2,"prevClose":546,"diff":-5.7999999999999545},"numTrans":552,"tradedShares":149119,"amount":81343387.7},"2024-01-11":{"price":{"open":567,"max":567,"min":545,"close":546,"prevClose":556.1,"diff":-10.100000000000023},"numTrans":494,"tradedShares":120373,"amount":66651016.7},"2024-01-10":{"price":{"open":547.9,"max":564.9,"min":536,"close":556.1,"prevClose":547.9,"diff":8.200000000000045},"numTrans":934,"tradedShares":232952,"amount":128697943.3},"2024-01-09":{"price":{"open":570,"max":578.9,"min":543.1,"close":547.9,"prevClose":563,"diff":-15.100000000000023},"numTrans":796,"tradedShares":179312,"amount":99285524.2},"2024-01-08":{"price":{"open":520,"max":571,"min":520,"close":563,"prevClose":521,"diff":42},"numTrans":1128,"tradedShares":261494,"amount":144609191.8},"2024-01-07":{"price":{"open":530,"max":539.9,"min":510,"close":521,"prevClose":530,"diff":-9},"numTrans":1233,"tradedShares":299893,"amount":156877281.3},"2024-01-04":{"price":{"open":527.3,"max":560,"min":527,"close":530,"prevClose":517,"diff":13},"numTrans":1422,"tradedShares":297376,"amount":162938444.7},"2024-01-03":{"price":{"open":479,"max":517,"min":476,"close":517,"prevClose":470,"diff":47},"numTrans":1493,"tradedShares":305032,"amount":154019590.4},"2024-01-02":{"price":{"open":452,"max":479,"min":445.9,"close":470,"prevClose":451.1,"diff":18.899999999999977},"numTrans":889,"tradedShares":272942,"amount":125348212.6},"2024-01-01":{"price":{"open":454,"max":474,"min":447,"close":451.1,"prevClose":449,"diff":2.1000000000000227},"numTrans":741,"tradedShares":204257,"amount":94454760},"2023-12-28":{"price":{"open":428,"max":454,"min":427.9,"close":449,"prevClose":430.1,"diff":18.899999999999977},"numTrans":572,"tradedShares":112609,"amount":50133868},"2023-12-27":{"price":{"open":422,"max":453.9,"min":422,"close":430.1,"prevClose":422,"diff":8.100000000000023},"numTrans":691,"tradedShares":131857,"amount":57624268.7},"2023-12-24":{"price":{"open":461.3,"max":486.9,"min":416,"close":422,"prevClose":452.3,"diff":-30.30000000000001},"numTrans":1261,"tradedShares":223347,"amount":101161784.6},"2023-12-21":{"price":{"open":425,"max":458.5,"min":425,"close":452.3,"prevClose":416.9,"diff":35.400000000000034},"numTrans":880,"tradedShares":209345,"amount":95298326.1},"2023-12-20":{"price":{"open":385,"max":416.9,"min":370,"close":416.9,"prevClose":379,"diff":37.89999999999998},"numTrans":628,"tradedShares":150685,"amount":60661161.9},"2023-12-19":{"price":{"open":375,"max":379,"min":356,"close":379,"prevClose":368,"diff":11},"numTrans":466,"tradedShares":108382,"amount":39911854.4},"2023-12-18":{"price":{"open":365,"max":376.9,"min":362,"close":368,"prevClose":360,"diff":8},"numTrans":448,"tradedShares":96713,"amount":35745473.6},"2023-12-17":{"price":{"open":342,"max":362,"min":330.3,"close":360,"prevClose":343,"diff":17},"numTrans":516,"tradedShares":135083,"amount":47772684.1},"2023-12-14":{"price":{"open":350.8,"max":350.8,"min":333,"close":343,"prevClose":344,"diff":-1},"numTrans":266,"tradedShares":59507,"amount":20272740},"2023-12-13":{"price":{"open":334,"max":347,"min":334,"close":344,"prevClose":331.4,"diff":12.600000000000023},"numTrans":424,"tradedShares":77796,"amount":26556777.6},"2023-12-12":{"price":{"open":315.1,"max":337.9,"min":315.1,"close":331.4,"prevClose":318,"diff":13.399999999999977},"numTrans":497,"tradedShares":115187,"amount":38049000.5},"2023-12-11":{"price":{"open":327,"max":327,"min":310,"close":318,"prevClose":321,"diff":-3},"numTrans":516,"tradedShares":152746,"amount":48561515.2},"2023-12-10":{"price":{"open":319,"max":336,"min":317,"close":321,"prevClose":313,"diff":8},"numTrans":66,"tradedShares":17805,"amount":5713351.5},"2023-12-07":{"price":{"open":299.4,"max":319,"min":299,"close":313,"prevClose":299.2,"diff":13.800000000000011},"numTrans":460,"tradedShares":101822,"amount":31631755.4},"2023-12-06":{"price":{"open":291,"max":300,"min":285,"close":299.2,"prevClose":286.2,"diff":13},"numTrans":339,"tradedShares":55316,"amount":16265916.5},"2023-12-05":{"price":{"open":311.7,"max":311.7,"min":280.6,"close":286.2,"prevClose":311.7,"diff":-25.5},"numTrans":717,"tradedShares":200950,"amount":57849537.6},"2023-12-04":{"price":{"open":339.4,"max":339.4,"min":311.7,"close":311.7,"prevClose":346.3,"diff":-34.60000000000002},"numTrans":88,"tradedShares":14245,"amount":4442380},"2023-12-03":{"price":{"open":392.3,"max":392.3,"min":346.3,"close":346.3,"prevClose":384.7,"diff":-38.39999999999998},"numTrans":94,"tradedShares":18060,"amount":6268234},"2023-11-30":{"price":{"open":399.8,"max":399.8,"min":376.6,"close":384.7,"prevClose":392,"diff":-7.300000000000011},"numTrans":63,"tradedShares":5757,"amount":2193693.7},"2023-11-29":{"price":{"open":396,"max":402.8,"min":387,"close":392,"prevClose":396,"diff":-4},"numTrans":88,"tradedShares":10715,"amount":4194401},"2023-11-28":{"price":{"open":404.9,"max":404.9,"min":389,"close":396,"prevClose":397.8,"diff":-1.8000000000000114},"numTrans":97,"tradedShares":10362,"amount":4063660.5},"2023-11-27":{"price":{"open":400,"max":407,"min":390,"close":397.8,"prevClose":402.8,"diff":-5},"numTrans":105,"tradedShares":15374,"amount":6097344},"2023-11-26":{"price":{"open":390,"max":404.9,"min":387.6,"close":402.8,"prevClose":393.9,"diff":8.900000000000034},"numTrans":106,"tradedShares":8041,"amount":3207298.7},"2023-11-23":{"price":{"open":378,"max":419.1,"min":373.4,"close":393.9,"prevClose":381,"diff":12.899999999999977},"numTrans":89,"tradedShares":4013,"amount":1562158.5},"2023-11-22":{"price":{"open":370,"max":390,"min":370,"close":381,"prevClose":376.9,"diff":4.100000000000023},"numTrans":50,"tradedShares":1410,"amount":531966},"2023-11-21":{"price":{"open":385,"max":390,"min":370,"close":376.9,"prevClose":385,"diff":-8.100000000000023},"numTrans":52,"tradedShares":3891,"amount":1462067.5},"2023-11-20":{"price":{"open":374,"max":395,"min":374,"close":385,"prevClose":380,"diff":5},"numTrans":52,"tradedShares":3595,"amount":1359221},"2023-11-09":{"price":{"open":399,"max":407,"min":374.6,"close":380,"prevClose":391.7,"diff":-11.699999999999989},"numTrans":43,"tradedShares":2037,"amount":776429},"2023-11-08":{"price":{"open":381.1,"max":394.7,"min":381.1,"close":391.7,"prevClose":383.5,"diff":8.199999999999989},"numTrans":36,"tradedShares":3140,"amount":1220602.6},"2023-11-07":{"price":{"open":392.5,"max":408.3,"min":380.8,"close":383.5,"prevClose":384.9,"diff":-1.3999999999999773},"numTrans":75,"tradedShares":4511,"amount":1768603},"2023-11-06":{"price":{"open":382.5,"max":395.7,"min":374.9,"close":384.9,"prevClose":375,"diff":9.899999999999977},"numTrans":67,"tradedShares":1914,"amount":735416},"2023-11-05":{"price":{"open":375.2,"max":380,"min":368.1,"close":375,"prevClose":380,"diff":-5},"numTrans":66,"tradedShares":5249,"amount":1955112},"2023-11-02":{"price":{"open":387.1,"max":388,"min":380,"close":380,"prevClose":394,"diff":-14},"numTrans":86,"tradedShares":9273,"amount":3548989.1},"2023-11-01":{"price":{"open":385.1,"max":394,"min":385.1,"close":394,"prevClose":390,"diff":4},"numTrans":49,"tradedShares":2990,"amount":1157234.3},"2023-10-31":{"price":{"open":397.8,"max":412,"min":386,"close":390,"prevClose":390,"diff":0},"numTrans":65,"tradedShares":2809,"amount":1091966.3},"2023-10-30":{"price":{"open":404.9,"max":404.9,"min":389.1,"close":390,"prevClose":397,"diff":-7},"numTrans":66,"tradedShares":4139,"amount":1623382.5},"2023-10-29":{"price":{"open":398,"max":405,"min":390,"close":397,"prevClose":398,"diff":-1},"numTrans":57,"tradedShares":3525,"amount":1391307.5},"2023-10-19":{"price":{"open":397,"max":402,"min":393,"close":398,"prevClose":403.9,"diff":-5.899999999999977},"numTrans":63,"tradedShares":7065,"amount":2792631.6},"2023-10-18":{"price":{"open":390.4,"max":404,"min":390.4,"close":403.9,"prevClose":392,"diff":11.899999999999977},"numTrans":45,"tradedShares":4572,"amount":1818574.2},"2023-10-17":{"price":{"open":395,"max":402.9,"min":385.3,"close":392,"prevClose":387.3,"diff":4.699999999999989},"numTrans":66,"tradedShares":2675,"amount":1042999.2},"2023-10-16":{"price":{"open":386,"max":400.8,"min":386,"close":387.3,"prevClose":393,"diff":-5.699999999999989},"numTrans":76,"tradedShares":2046,"amount":800167.9},"2023-10-12":{"price":{"open":397,"max":402,"min":392.6,"close":393,"prevClose":400,"diff":-7},"numTrans":101,"tradedShares":7295,"amount":2884188.2},"2023-10-11":{"price":{"open":398,"max":416,"min":396.6,"close":400,"prevClose":401,"diff":-1},"numTrans":104,"tradedShares":7323,"amount":2943953.7},"2023-10-10":{"price":{"open":412,"max":412,"min":397.9,"close":401,"prevClose":412,"diff":-11},"numTrans":74,"tradedShares":6208,"amount":2502907.7},"2023-10-09":{"price":{"open":403,"max":413.9,"min":403,"close":412,"prevClose":410,"diff":2},"numTrans":89,"tradedShares":4999,"amount":2039157},"2023-10-08":{"price":{"open":415,"max":415.2,"min":405,"close":410,"prevClose":419,"diff":-9},"numTrans":116,"tradedShares":15726,"amount":6436716.8},"2023-10-05":{"price":{"open":435,"max":435,"min":417,"close":419,"prevClose":427,"diff":-8},"numTrans":51,"tradedShares":1810,"amount":761030},"2023-10-04":{"price":{"open":426,"max":441,"min":410.3,"close":427,"prevClose":418,"diff":9},"numTrans":78,"tradedShares":3598,"amount":1523149},"2023-10-03":{"price":{"open":422.1,"max":425,"min":415,"close":418,"prevClose":427.1,"diff":-9.100000000000023},"numTrans":83,"tradedShares":7870,"amount":3308252},"2023-10-02":{"price":{"open":430,"max":430.1,"min":423.7,"close":427.1,"prevClose":436,"diff":-8.899999999999977},"numTrans":82,"tradedShares":6694,"amount":2861243.9},"2023-10-01":{"price":{"open":430.3,"max":437.8,"min":427,"close":436,"prevClose":439,"diff":-3},"numTrans":74,"tradedShares":6623,"amount":2859610.1},"2023-09-27":{"price":{"open":436,"max":450,"min":432.1,"close":439,"prevClose":444,"diff":-5},"numTrans":66,"tradedShares":6748,"amount":2939922.2},"2023-09-26":{"price":{"open":452,"max":459.9,"min":434,"close":444,"prevClose":445,"diff":-1},"numTrans":157,"tradedShares":21330,"amount":9339977.7},"2023-09-25":{"price":{"open":437.2,"max":453,"min":437.2,"close":445,"prevClose":446,"diff":-1},"numTrans":61,"tradedShares":3092,"amount":1370035.2},"2023-09-24":{"price":{"open":443.1,"max":459,"min":439.5,"close":446,"prevClose":450,"diff":-4},"numTrans":92,"tradedShares":7811,"amount":3486670.5},"2023-09-21":{"price":{"open":457.9,"max":461,"min":449,"close":450,"prevClose":449.8,"diff":0.19999999999998863},"numTrans":161,"tradedShares":25375,"amount":11554886.9},"2023-09-19":{"price":{"open":431,"max":449.8,"min":431,"close":449.8,"prevClose":438.8,"diff":11},"numTrans":75,"tradedShares":4540,"amount":2016655.4},"2023-09-18":{"price":{"open":441,"max":441,"min":430,"close":438.8,"prevClose":433,"diff":5.800000000000011},"numTrans":46,"tradedShares":1828,"amount":792717.4},"2023-09-17":{"price":{"open":437.1,"max":439,"min":425,"close":433,"prevClose":445,"diff":-12},"numTrans":66,"tradedShares":5817,"amount":2512254.3},"2023-09-13":{"price":{"open":430.1,"max":452,"min":430.1,"close":445,"prevClose":435,"diff":10},"numTrans":92,"tradedShares":5261,"amount":2336585.5},"2023-09-12":{"price":{"open":443,"max":448,"min":427,"close":435,"prevClose":443,"diff":-8},"numTrans":83,"tradedShares":6129,"amount":2687041.2},"2023-09-11":{"price":{"open":425,"max":443,"min":420,"close":443,"prevClose":428.4,"diff":14.600000000000023},"numTrans":79,"tradedShares":7645,"amount":3345546.1},"2023-09-10":{"price":{"open":426,"max":434,"min":418.1,"close":428.4,"prevClose":421,"diff":7.399999999999977},"numTrans":68,"tradedShares":2892,"amount":1220387},"2023-09-07":{"price":{"open":440,"max":440,"min":417,"close":421,"prevClose":440,"diff":-19},"numTrans":109,"tradedShares":9670,"amount":4099692.6},"2023-09-05":{"price":{"open":437,"max":443,"min":423.6,"close":440,"prevClose":445,"diff":-5},"numTrans":81,"tradedShares":8681,"amount":3751556.2},"2023-09-04":{"price":{"open":432.1,"max":445,"min":430,"close":445,"prevClose":436.9,"diff":8.100000000000023},"numTrans":94,"tradedShares":5490,"amount":2410827.5},"2023-09-03":{"price":{"open":435.8,"max":453,"min":433,"close":436.9,"prevClose":444.6,"diff":-7.7000000000000455},"numTrans":84,"tradedShares":2291,"amount":999340.4},"2023-08-30":{"price":{"open":442,"max":445,"min":440,"close":444.6,"prevClose":447,"diff":-2.3999999999999773},"numTrans":55,"tradedShares":1665,"amount":736765},"2023-08-29":{"price":{"open":440,"max":448.8,"min":439,"close":447,"prevClose":444,"diff":3},"numTrans":81,"tradedShares":5855,"amount":2586981.1},"2023-08-28":{"price":{"open":435.1,"max":449,"min":435.1,"close":444,"prevClose":443.8,"diff":0.19999999999998863},"numTrans":82,"tradedShares":6744,"amount":2986407.6},"2023-08-27":{"price":{"open":447,"max":447,"min":435,"close":443.8,"prevClose":445,"diff":-1.1999999999999886},"numTrans":105,"tradedShares":4769,"amount":2086710},"2023-08-24":{"price":{"open":450,"max":460,"min":440,"close":445,"prevClose":453,"diff":-8},"numTrans":101,"tradedShares":7048,"amount":3149688},"2023-08-23":{"price":{"open":447,"max":469,"min":446,"close":453,"prevClose":453.4,"diff":-0.39999999999997726},"numTrans":109,"tradedShares":7149,"amount":3269473.4},"2023-08-22":{"price":{"open":448.8,"max":453.4,"min":432,"close":453.4,"prevClose":440,"diff":13.399999999999977},"numTrans":91,"tradedShares":5824,"amount":2595769.9},"2023-08-21":{"price":{"open":440,"max":457,"min":438,"close":440,"prevClose":447,"diff":-7},"numTrans":74,"tradedShares":3689,"amount":1631045},"2023-08-20":{"price":{"open":455,"max":464,"min":447,"close":447,"prevClose":458,"diff":-11},"numTrans":76,"tradedShares":8354,"amount":3799142},"2023-08-17":{"price":{"open":452.1,"max":465,"min":452.1,"close":458,"prevClose":455,"diff":3},"numTrans":103,"tradedShares":10463,"amount":4811840.2},"2023-08-16":{"price":{"open":454.8,"max":458.8,"min":445.8,"close":455,"prevClose":464,"diff":-9},"numTrans":128,"tradedShares":11144,"amount":5017092.9},"2023-08-15":{"price":{"open":463.6,"max":472.8,"min":456,"close":464,"prevClose":473,"diff":-9},"numTrans":111,"tradedShares":8873,"amount":4112198},"2023-08-14":{"price":{"open":491,"max":491,"min":468,"close":473,"prevClose":487,"diff":-14},"numTrans":116,"tradedShares":6911,"amount":3288205},"2023-08-13":{"price":{"open":475,"max":488,"min":466,"close":487,"prevClose":480,"diff":7},"numTrans":130,"tradedShares":6516,"amount":3118901.7},"2023-08-10":{"price":{"open":477,"max":484.5,"min":467.7,"close":480,"prevClose":477,"diff":3},"numTrans":111,"tradedShares":9952,"amount":4734215.9},"2023-08-09":{"price":{"open":464,"max":477.3,"min":457.2,"close":477,"prevClose":472.8,"diff":4.199999999999989},"numTrans":164,"tradedShares":15752,"amount":7317993.1},"2023-08-08":{"price":{"open":471,"max":485.5,"min":465.5,"close":472.8,"prevClose":470,"diff":2.8000000000000114},"numTrans":114,"tradedShares":9290,"amount":4394550},"2023-08-07":{"price":{"open":480,"max":489,"min":464.2,"close":470,"prevClose":473,"diff":-3},"numTrans":114,"tradedShares":11162,"amount":5285052.1},"2023-08-06":{"price":{"open":498.7,"max":498.7,"min":469,"close":473,"prevClose":489,"diff":-16},"numTrans":109,"tradedShares":11869,"amount":5694402},"2023-08-03":{"price":{"open":500,"max":505,"min":486,"close":489,"prevClose":496,"diff":-7},"numTrans":138,"tradedShares":11849,"amount":5845247.4},"2023-08-02":{"price":{"open":493,"max":500,"min":486,"close":496,"prevClose":493,"diff":3},"numTrans":79,"tradedShares":7218,"amount":3548295},"2023-08-01":{"price":{"open":514,"max":514,"min":491,"close":493,"prevClose":504.1,"diff":-11.100000000000023},"numTrans":140,"tradedShares":18481,"amount":9208202.5},"2023-07-31":{"price":{"open":504.9,"max":516.5,"min":504.1,"close":504.1,"prevClose":513,"diff":-8.899999999999977},"numTrans":101,"tradedShares":6812,"amount":3468621.5},"2023-07-30":{"price":{"open":507,"max":518.2,"min":503.1,"close":513,"prevClose":510,"diff":3},"numTrans":138,"tradedShares":10418,"amount":5291929.7},"2023-07-27":{"price":{"open":521.8,"max":527,"min":510,"close":510,"prevClose":514,"diff":-4},"numTrans":218,"tradedShares":22820,"amount":11865312.9},"2023-07-26":{"price":{"open":513.2,"max":529,"min":511.6,"close":514,"prevClose":519,"diff":-5},"numTrans":116,"tradedShares":11400,"amount":5888749.5},"2023-07-25":{"price":{"open":519,"max":523,"min":513.1,"close":519,"prevClose":519,"diff":0},"numTrans":127,"tradedShares":12101,"amount":6272149.7},"2023-07-24":{"price":{"open":524.3,"max":535,"min":515,"close":519,"prevClose":535,"diff":-16},"numTrans":251,"tradedShares":37883,"amount":19787681.4},"2023-07-23":{"price":{"open":509,"max":535,"min":509,"close":535,"prevClose":508,"diff":27},"numTrans":344,"tradedShares":50624,"amount":26518691.7},"2023-07-20":{"price":{"open":505.1,"max":516,"min":505.1,"close":508,"prevClose":508.2,"diff":-0.19999999999998863},"numTrans":156,"tradedShares":19372,"amount":9888157.8},"2023-07-19":{"price":{"open":505.7,"max":518,"min":505.7,"close":508.2,"prevClose":513.3,"diff":-5.099999999999966},"numTrans":122,"tradedShares":18260,"amount":9331307.8},"2023-07-18":{"price":{"open":513,"max":531,"min":513,"close":513.3,"prevClose":521,"diff":-7.7000000000000455},"numTrans":147,"tradedShares":17290,"amount":8964554.9},"2023-07-17":{"price":{"open":510,"max":525,"min":501,"close":521,"prevClose":513,"diff":8},"numTrans":182,"tradedShares":22151,"amount":11416405.2},"2023-07-16":{"price":{"open":521,"max":530,"min":500,"close":513,"prevClose":511,"diff":2},"numTrans":166,"tradedShares":20313,"amount":10270758.7},"2023-07-13":{"price":{"open":527.1,"max":536.9,"min":511,"close":511,"prevClose":527,"diff":-16},"numTrans":149,"tradedShares":21461,"amount":11232333.5},"2023-07-12":{"price":{"open":511.1,"max":549,"min":511.1,"close":527,"prevClose":520.4,"diff":6.600000000000023},"numTrans":180,"tradedShares":24838,"amount":13134002.9},"2023-07-11":{"price":{"open":534,"max":534.4,"min":501.1,"close":520.4,"prevClose":524.3,"diff":-3.8999999999999773},"numTrans":233,"tradedShares":35966,"amount":18564596.5},"2023-07-10":{"price":{"open":545,"max":545.1,"min":524.3,"close":524.3,"prevClose":535,"diff":-10.700000000000045},"numTrans":154,"tradedShares":12862,"amount":6814187.3},"2023-07-09":{"price":{"open":526,"max":540,"min":526,"close":535,"prevClose":530,"diff":5},"numTrans":270,"tradedShares":27678,"amount":14709579.5},"2023-07-06":{"price":{"open":540,"max":540.6,"min":521,"close":530,"prevClose":530,"diff":0},"numTrans":261,"tradedShares":25718,"amount":13644795.2},"2023-07-05":{"price":{"open":548,"max":552.3,"min":528,"close":530,"prevClose":548,"diff":-18},"numTrans":229,"tradedShares":27515,"amount":14713901.6},"2023-07-04":{"price":{"open":530,"max":548.7,"min":527,"close":548,"prevClose":538,"diff":10},"numTrans":249,"tradedShares":31675,"amount":16937590.7},"2023-07-03":{"price":{"open":523.2,"max":543.7,"min":520,"close":538,"prevClose":528,"diff":10},"numTrans":337,"tradedShares":51722,"amount":27464829.2},"2023-07-02":{"price":{"open":570,"max":570,"min":526,"close":528,"prevClose":564,"diff":-36},"numTrans":442,"tradedShares":62104,"amount":34022953.4},"2023-06-28":{"price":{"open":550,"max":580,"min":527.5,"close":564,"prevClose":540,"diff":24},"numTrans":503,"tradedShares":80215,"amount":44172554.8},"2023-06-27":{"price":{"open":500,"max":540,"min":500,"close":540,"prevClose":500,"diff":40},"numTrans":527,"tradedShares":75541,"amount":39576442.9},"2023-06-26":{"price":{"open":502.1,"max":515,"min":498,"close":500,"prevClose":508,"diff":-8},"numTrans":191,"tradedShares":21775,"amount":11020537},"2023-06-25":{"price":{"open":489,"max":509,"min":489,"close":508,"prevClose":484,"diff":24},"numTrans":274,"tradedShares":24525,"amount":12261170.8},"2023-06-22":{"price":{"open":480.2,"max":506,"min":480,"close":484,"prevClose":490,"diff":-6},"numTrans":126,"tradedShares":14783,"amount":7195261.8},"2023-06-21":{"price":{"open":495.3,"max":510,"min":490,"close":490,"prevClose":505,"diff":-15},"numTrans":118,"tradedShares":15225,"amount":7608059.7},"2023-06-20":{"price":{"open":505.5,"max":520.2,"min":499.1,"close":505,"prevClose":510,"diff":-5},"numTrans":209,"tradedShares":31437,"amount":16063322.6},"2023-06-19":{"price":{"open":504,"max":511,"min":493.8,"close":510,"prevClose":512,"diff":-2},"numTrans":166,"tradedShares":22429,"amount":11253722.9},"2023-06-18":{"price":{"open":497,"max":514,"min":497,"close":512,"prevClose":506,"diff":6},"numTrans":170,"tradedShares":16023,"amount":8131614.3},"2023-06-15":{"price":{"open":503.1,"max":510,"min":492.5,"close":506,"prevClose":512,"diff":-6},"numTrans":190,"tradedShares":20363,"amount":10172596},"2023-06-14":{"price":{"open":518,"max":526,"min":500,"close":512,"prevClose":510,"diff":2},"numTrans":219,"tradedShares":24096,"amount":12340458.8},"2023-06-13":{"price":{"open":488.1,"max":524.1,"min":488.1,"close":510,"prevClose":493,"diff":17},"numTrans":234,"tradedShares":23412,"amount":11985847.5},"2023-06-12":{"price":{"open":501,"max":507,"min":488,"close":493,"prevClose":507.9,"diff":-14.899999999999977},"numTrans":145,"tradedShares":15953,"amount":7894670.6},"2023-06-11":{"price":{"open":492,"max":508,"min":483.3,"close":507.9,"prevClose":484,"diff":23.899999999999977},"numTrans":293,"tradedShares":35833,"amount":17955481.7},"2023-06-08":{"price":{"open":470,"max":489.8,"min":464.1,"close":484,"prevClose":470,"diff":14},"numTrans":136,"tradedShares":20370,"amount":9744278.7},"2023-06-07":{"price":{"open":477,"max":483,"min":467.7,"close":470,"prevClose":477,"diff":-7},"numTrans":57,"tradedShares":5450,"amount":2578584.5},"2023-06-06":{"price":{"open":460,"max":479,"min":455.5,"close":477,"prevClose":461,"diff":16},"numTrans":95,"tradedShares":8062,"amount":3795800.2},"2023-06-05":{"price":{"open":466,"max":472,"min":456.2,"close":461,"prevClose":465,"diff":-4},"numTrans":117,"tradedShares":9035,"amount":4188205.9},"2023-06-04":{"price":{"open":460,"max":469.5,"min":453,"close":465,"prevClose":451.9,"diff":13.100000000000023},"numTrans":97,"tradedShares":6422,"amount":2973384.3},"2023-06-01":{"price":{"open":442,"max":452,"min":437.3,"close":451.9,"prevClose":449,"diff":2.8999999999999773},"numTrans":98,"tradedShares":9847,"amount":4406434.8},"2023-05-31":{"price":{"open":445,"max":470,"min":436.4,"close":449,"prevClose":454,"diff":-5},"numTrans":140,"tradedShares":14727,"amount":6560379.6},"2023-05-30":{"price":{"open":463.6,"max":463.6,"min":445.5,"close":454,"prevClose":473,"diff":-19},"numTrans":120,"tradedShares":12166,"amount":5534723.5},"2023-05-28":{"price":{"open":475,"max":493,"min":466,"close":473,"prevClose":484,"diff":-11},"numTrans":119,"tradedShares":12111,"amount":5773595.1},"2023-05-24":{"price":{"open":463.6,"max":484,"min":460,"close":484,"prevClose":473,"diff":11},"numTrans":143,"tradedShares":15615,"amount":7430023.2},"2023-05-23":{"price":{"open":444,"max":473,"min":444,"close":473,"prevClose":453,"diff":20},"numTrans":197,"tradedShares":14269,"amount":6651157.4},"2023-05-22":{"price":{"open":439,"max":467,"min":439,"close":453,"prevClose":447.9,"diff":5.100000000000023},"numTrans":108,"tradedShares":6680,"amount":3040528.7},"2023-05-21":{"price":{"open":460,"max":460.3,"min":435.2,"close":447.9,"prevClose":451.3,"diff":-3.400000000000034},"numTrans":115,"tradedShares":8369,"amount":3725136.4},"2023-05-18":{"price":{"open":436,"max":462,"min":433,"close":451.3,"prevClose":444.7,"diff":6.600000000000023},"numTrans":148,"tradedShares":7519,"amount":3376289.5},"2023-05-17":{"price":{"open":433,"max":444.7,"min":428.3,"close":444.7,"prevClose":436.5,"diff":8.199999999999989},"numTrans":82,"tradedShares":2573,"amount":1134545.3},"2023-05-16":{"price":{"open":432.1,"max":439,"min":427.1,"close":436.5,"prevClose":439.9,"diff":-3.3999999999999773},"numTrans":43,"tradedShares":1276,"amount":554283},"2023-05-15":{"price":{"open":428.5,"max":439.9,"min":428.3,"close":439.9,"prevClose":436.9,"diff":3},"numTrans":71,"tradedShares":5255,"amount":2269990.5},"2023-05-14":{"price":{"open":434.2,"max":436.9,"min":428.1,"close":436.9,"prevClose":442,"diff":-5.100000000000023},"numTrans":59,"tradedShares":3601,"amount":1555835.9},"2023-05-11":{"price":{"open":432,"max":442,"min":432,"close":442,"prevClose":440,"diff":2},"numTrans":37,"tradedShares":614,"amount":267912.3},"2023-05-10":{"price":{"open":436,"max":442,"min":430.6,"close":440,"prevClose":444,"diff":-4},"numTrans":34,"tradedShares":1105,"amount":483585},"2023-05-09":{"price":{"open":430.3,"max":447,"min":430.3,"close":444,"prevClose":439,"diff":5},"numTrans":62,"tradedShares":1604,"amount":702079.3},"2023-05-08":{"price":{"open":434,"max":440,"min":430,"close":439,"prevClose":437.2,"diff":1.8000000000000114},"numTrans":62,"tradedShares":5074,"amount":2193273},"2023-05-07":{"price":{"open":440,"max":443,"min":435,"close":437.2,"prevClose":445.2,"diff":-8},"numTrans":35,"tradedShares":2859,"amount":1252855.2},"2023-05-04":{"price":{"open":440.1,"max":453,"min":432.2,"close":445.2,"prevClose":449,"diff":-3.8000000000000114},"numTrans":57,"tradedShares":2850,"amount":1266943},"2023-05-03":{"price":{"open":440.5,"max":449,"min":434,"close":449,"prevClose":448,"diff":1},"numTrans":54,"tradedShares":2663,"amount":1176217.5},"2023-05-02":{"price":{"open":441.1,"max":458.4,"min":441.1,"close":448,"prevClose":449.5,"diff":-1.5},"numTrans":80,"tradedShares":5687,"amount":2532190.5},"2023-04-30":{"price":{"open":441.2,"max":450,"min":441.2,"close":449.5,"prevClose":450,"diff":-0.5},"numTrans":47,"tradedShares":1245,"amount":553529.9},"2023-04-27":{"price":{"open":443,"max":454.8,"min":443,"close":450,"prevClose":451.9,"diff":-1.8999999999999773},"numTrans":62,"tradedShares":2647,"amount":1185825.8},"2023-04-26":{"price":{"open":448.4,"max":457.3,"min":439.7,"close":451.9,"prevClose":457.5,"diff":-5.600000000000023},"numTrans":38,"tradedShares":1390,"amount":622765},"2023-04-25":{"price":{"open":444.9,"max":462.9,"min":442.1,"close":457.5,"prevClose":453.9,"diff":3.6000000000000227},"numTrans":46,"tradedShares":2236,"amount":1012053.8},"2023-04-24":{"price":{"open":436.3,"max":453.9,"min":436.3,"close":453.9,"prevClose":445,"diff":8.899999999999977},"numTrans":61,"tradedShares":2889,"amount":1291271},"2023-04-23":{"price":{"open":445.9,"max":459,"min":445,"close":445,"prevClose":454.9,"diff":-9.899999999999977},"numTrans":86,"tradedShares":8096,"amount":3638436},"2023-04-20":{"price":{"open":450,"max":465,"min":445,"close":454.9,"prevClose":458.9,"diff":-4},"numTrans":49,"tradedShares":949,"amount":430234.9},"2023-04-19":{"price":{"open":452.8,"max":464.1,"min":443.8,"close":458.9,"prevClose":455,"diff":3.8999999999999773},"numTrans":57,"tradedShares":2733,"amount":1242754.4},"2023-04-18":{"price":{"open":452.8,"max":464,"min":440,"close":455,"prevClose":462,"diff":-7},"numTrans":52,"tradedShares":3418,"amount":1549280.2},"2023-04-17":{"price":{"open":475,"max":475,"min":450.1,"close":462,"prevClose":468,"diff":-6},"numTrans":63,"tradedShares":4142,"amount":1882344.7},"2023-04-16":{"price":{"open":451,"max":470,"min":451,"close":468,"prevClose":460.1,"diff":7.899999999999977},"numTrans":65,"tradedShares":1597,"amount":738823.1},"2023-04-13":{"price":{"open":486,"max":486,"min":460.1,"close":460.1,"prevClose":484,"diff":-23.899999999999977},"numTrans":105,"tradedShares":8047,"amount":3772393.6},"2023-04-12":{"price":{"open":440.1,"max":486,"min":440.1,"close":484,"prevClose":449,"diff":35},"numTrans":123,"tradedShares":6884,"amount":3197173.7},"2023-04-11":{"price":{"open":433.2,"max":449,"min":430,"close":449,"prevClose":442,"diff":7},"numTrans":80,"tradedShares":3556,"amount":1559672.9},"2023-04-10":{"price":{"open":440,"max":442,"min":425,"close":442,"prevClose":438.6,"diff":3.3999999999999773},"numTrans":75,"tradedShares":5038,"amount":2200483.7},"2023-04-09":{"price":{"open":429,"max":445.6,"min":425.7,"close":438.6,"prevClose":437,"diff":1.6000000000000227},"numTrans":109,"tradedShares":7738,"amount":3334100.9},"2023-04-06":{"price":{"open":447,"max":447,"min":436.1,"close":437,"prevClose":447.9,"diff":-10.899999999999977},"numTrans":65,"tradedShares":4033,"amount":1765583},"2023-04-05":{"price":{"open":440,"max":454,"min":432.1,"close":447.9,"prevClose":448,"diff":-0.10000000000002274},"numTrans":84,"tradedShares":4751,"amount":2099782.5},"2023-04-04":{"price":{"open":435,"max":449.8,"min":428,"close":448,"prevClose":435,"diff":13},"numTrans":109,"tradedShares":7169,"amount":3121801.5},"2023-04-03":{"price":{"open":441,"max":450,"min":435,"close":435,"prevClose":449.9,"diff":-14.899999999999977},"numTrans":129,"tradedShares":11814,"amount":5192896.2},"2023-04-02":{"price":{"open":455,"max":455,"min":443.2,"close":449.9,"prevClose":451,"diff":-1.1000000000000227},"numTrans":51,"tradedShares":1656,"amount":742025},"2023-03-30":{"price":{"open":453,"max":459,"min":451,"close":451,"prevClose":461,"diff":-10},"numTrans":50,"tradedShares":2073,"amount":940269.2},"2023-03-29":{"price":{"open":460,"max":462,"min":447.1,"close":461,"prevClose":465,"diff":-4},"numTrans":79,"tradedShares":7501,"amount":3400988.1},"2023-03-28":{"price":{"open":460,"max":470,"min":451,"close":465,"prevClose":460,"diff":5},"numTrans":106,"tradedShares":5269,"amount":2418251},"2023-03-27":{"price":{"open":434,"max":461.9,"min":434,"close":460,"prevClose":441,"diff":19},"numTrans":136,"tradedShares":10443,"amount":4652970.8},"2023-03-26":{"price":{"open":448.9,"max":457,"min":440.1,"close":441,"prevClose":458,"diff":-17},"numTrans":74,"tradedShares":1808,"amount":807414.9},"2023-03-23":{"price":{"open":456,"max":459.9,"min":445,"close":458,"prevClose":465,"diff":-7},"numTrans":59,"tradedShares":3575,"amount":1617208.8},"2023-03-22":{"price":{"open":460.5,"max":475,"min":456,"close":465,"prevClose":468.8,"diff":-3.8000000000000114},"numTrans":70,"tradedShares":3296,"amount":1522198.4},"2023-03-20":{"price":{"open":448.1,"max":468.8,"min":448.1,"close":468.8,"prevClose":457,"diff":11.800000000000011},"numTrans":71,"tradedShares":3710,"amount":1716929.9},"2023-03-19":{"price":{"open":460.6,"max":461,"min":451.4,"close":457,"prevClose":470,"diff":-13},"numTrans":69,"tradedShares":4626,"amount":2109506},"2023-03-16":{"price":{"open":454.7,"max":470,"min":450,"close":470,"prevClose":463.9,"diff":6.100000000000023},"numTrans":66,"tradedShares":4738,"amount":2157605.4},"2023-03-15":{"price":{"open":460,"max":465,"min":450.8,"close":463.9,"prevClose":464.8,"diff":-0.9000000000000341},"numTrans":67,"tradedShares":6825,"amount":3111067.9},"2023-03-14":{"price":{"open":465,"max":475,"min":455.7,"close":464.8,"prevClose":464,"diff":0.8000000000000114},"numTrans":77,"tradedShares":3483,"amount":1613805},"2023-03-13":{"price":{"open":477,"max":483,"min":455,"close":464,"prevClose":473.9,"diff":-9.899999999999977},"numTrans":65,"tradedShares":3386,"amount":1557199.8},"2023-03-12":{"price":{"open":473.5,"max":485,"min":465,"close":473.9,"prevClose":481,"diff":-7.100000000000023},"numTrans":72,"tradedShares":5771,"amount":2714070.4},"2023-03-09":{"price":{"open":478,"max":483,"min":459.7,"close":481,"prevClose":469,"diff":12},"numTrans":84,"tradedShares":4980,"amount":2350679.5},"2023-03-07":{"price":{"open":450.1,"max":469,"min":450.1,"close":469,"prevClose":458.9,"diff":10.100000000000023},"numTrans":77,"tradedShares":5568,"amount":2566003},"2023-03-05":{"price":{"open":456,"max":470,"min":442,"close":458.9,"prevClose":465,"diff":-6.100000000000023},"numTrans":57,"tradedShares":5697,"amount":2554187},"2023-03-02":{"price":{"open":461.1,"max":485,"min":460,"close":465,"prevClose":467.4,"diff":-2.3999999999999773},"numTrans":62,"tradedShares":3542,"amount":1643638},"2023-03-01":{"price":{"open":476,"max":478,"min":467.4,"close":467.4,"prevClose":485,"diff":-17.600000000000023},"numTrans":57,"tradedShares":3816,"amount":1792735},"2023-02-28":{"price":{"open":480,"max":489,"min":477,"close":485,"prevClose":486,"diff":-1},"numTrans":61,"tradedShares":3215,"amount":1544273.1},"2023-02-27":{"price":{"open":475,"max":498,"min":468,"close":486,"prevClose":480,"diff":6},"numTrans":84,"tradedShares":3814,"amount":1809371.2},"2023-02-26":{"price":{"open":477,"max":485,"min":461.3,"close":480,"prevClose":480,"diff":0},"numTrans":84,"tradedShares":7805,"amount":3685055},"2023-02-23":{"price":{"open":485.1,"max":485.1,"min":473,"close":480,"prevClose":495,"diff":-15},"numTrans":85,"tradedShares":5328,"amount":2541458.3},"2023-02-22":{"price":{"open":476.1,"max":498,"min":476.1,"close":495,"prevClose":485,"diff":10},"numTrans":84,"tradedShares":3084,"amount":1518033.5},"2023-02-20":{"price":{"open":478.7,"max":488,"min":470,"close":485,"prevClose":488,"diff":-3},"numTrans":68,"tradedShares":2967,"amount":1417110.9},"2023-02-16":{"price":{"open":477.1,"max":490,"min":477.1,"close":488,"prevClose":485,"diff":3},"numTrans":115,"tradedShares":8883,"amount":4285730.2},"2023-02-15":{"price":{"open":483.2,"max":501,"min":483.2,"close":485,"prevClose":492,"diff":-7},"numTrans":84,"tradedShares":5954,"amount":2918049.9},"2023-02-14":{"price":{"open":490,"max":499,"min":488.1,"close":492,"prevClose":497.5,"diff":-5.5},"numTrans":85,"tradedShares":5651,"amount":2780910.2},"2023-02-12":{"price":{"open":504,"max":504,"min":490,"close":497.5,"prevClose":513,"diff":-15.5},"numTrans":119,"tradedShares":14821,"amount":7331093.8},"2023-02-09":{"price":{"open":504.3,"max":515.1,"min":502,"close":513,"prevClose":514.5,"diff":-1.5},"numTrans":85,"tradedShares":7960,"amount":4043677.3},"2023-02-08":{"price":{"open":518,"max":524,"min":510,"close":514.5,"prevClose":518,"diff":-3.5},"numTrans":152,"tradedShares":19666,"amount":10155121.2},"2023-02-07":{"price":{"open":495,"max":518,"min":487,"close":518,"prevClose":490,"diff":28},"numTrans":168,"tradedShares":15268,"amount":7766150.2},"2023-02-06":{"price":{"open":490,"max":500,"min":481.1,"close":490,"prevClose":499.1,"diff":-9.100000000000023},"numTrans":104,"tradedShares":9569,"amount":4698037},"2023-02-05":{"price":{"open":504,"max":504,"min":486,"close":499.1,"prevClose":495,"diff":4.100000000000023},"numTrans":80,"tradedShares":3523,"amount":1735894.3},"2023-02-02":{"price":{"open":495.1,"max":506.9,"min":488,"close":495,"prevClose":502,"diff":-7},"numTrans":92,"tradedShares":7979,"amount":3957542.3},"2023-02-01":{"price":{"open":495,"max":506,"min":490.1,"close":502,"prevClose":499,"diff":3},"numTrans":110,"tradedShares":8597,"amount":4297805.5},"2023-01-31":{"price":{"open":500,"max":513,"min":491.3,"close":499,"prevClose":495,"diff":4},"numTrans":135,"tradedShares":9051,"amount":4533658.5},"2023-01-30":{"price":{"open":515.1,"max":524.2,"min":493,"close":495,"prevClose":519,"diff":-24},"numTrans":150,"tradedShares":20433,"amount":10361616.9},"2023-01-29":{"price":{"open":522.4,"max":532,"min":518.5,"close":519,"prevClose":533,"diff":-14},"numTrans":113,"tradedShares":11015,"amount":5770662.9},"2023-01-26":{"price":{"open":542.6,"max":548,"min":522.3,"close":533,"prevClose":532,"diff":1},"numTrans":193,"tradedShares":24850,"amount":13344350.7},"2024-01-24":{"price":{"open":612,"max":628,"min":600,"close":602,"prevClose":610,"diff":-8},"numTrans":663,"tradedShares":196002,"amount":120671892},"2024-01-25":{"price":{"open":604,"max":609.9,"min":586.2,"close":590,"prevClose":602,"diff":-12},"numTrans":540,"tradedShares":130099,"amount":77413653.5},"2024-01-28":{"price":{"open":599,"max":609,"min":579.1,"close":596.4,"prevClose":590,"diff":6.399999999999977},"numTrans":612,"tradedShares":157492,"amount":93118886},"2024-02-13":{"price":{"open":614,"max":614,"min":596,"close":596.3,"prevClose":614,"diff":-17.700000000000045},"numTrans":614,"tradedShares":117536,"amount":70962410.7},"2024-02-12":{"price":{"open":605,"max":622,"min":603,"close":614,"prevClose":607,"diff":7},"numTrans":993,"tradedShares":265514,"amount":163025176.2},"2024-02-11":{"price":{"open":595.1,"max":609,"min":595,"close":607,"prevClose":590,"diff":17},"numTrans":830,"tradedShares":199833,"amount":120434437.7},"2024-02-08":{"price":{"open":603.8,"max":603.8,"min":586,"close":590,"prevClose":592,"diff":-2},"numTrans":473,"tradedShares":117261,"amount":69269530.7},"2024-02-07":{"price":{"open":598,"max":603,"min":590,"close":592,"prevClose":592,"diff":0},"numTrans":302,"tradedShares":64843,"amount":38595107.4},"2024-02-06":{"price":{"open":596,"max":600,"min":587,"close":592,"prevClose":589.9,"diff":2.1000000000000227},"numTrans":317,"tradedShares":72468,"amount":43142654.3},"2024-02-05":{"price":{"open":596,"max":600,"min":578,"close":589.9,"prevClose":589,"diff":0.8999999999999773},"numTrans":341,"tradedShares":71657,"amount":42015110.5},"2024-02-04":{"price":{"open":598,"max":605,"min":586,"close":589,"prevClose":597,"diff":-8},"numTrans":353,"tradedShares":60242,"amount":35630638.2},"2024-02-01":{"price":{"open":603,"max":614,"min":594,"close":597,"prevClose":613,"diff":-16},"numTrans":668,"tradedShares":143134,"amount":86061421.3},"2024-01-31":{"price":{"open":600,"max":628.9,"min":595.1,"close":613,"prevClose":592,"diff":21},"numTrans":1644,"tradedShares":422853,"amount":260172364.4},"2024-01-30":{"price":{"open":600,"max":606,"min":581.1,"close":592,"prevClose":589,"diff":3},"numTrans":490,"tradedShares":100943,"amount":60300150.3},"2024-01-29":{"price":{"open":585,"max":613,"min":583,"close":589,"prevClose":596.4,"diff":-7.399999999999977},"numTrans":604,"tradedShares":186211,"amount":110548077.6},"2024-06-11":{"price":{"open":653,"max":726,"min":653,"close":721,"prevClose":661,"diff":60},"numTrans":1500,"tradedShares":525185,"amount":363092910.4},"2024-06-10":{"price":{"open":641.1,"max":715,"min":641.1,"close":661,"prevClose":650,"diff":11},"numTrans":1638,"tradedShares":627676,"amount":418763206},"2024-06-09":{"price":{"open":603,"max":660,"min":603,"close":650,"prevClose":615,"diff":35},"numTrans":1924,"tradedShares":502421,"amount":320394568.3},"2024-06-06":{"price":{"open":593,"max":618,"min":593,"close":615,"prevClose":605,"diff":10},"numTrans":938,"tradedShares":306300,"amount":186804917.1},"2024-06-05":{"price":{"open":600,"max":610,"min":588,"close":605,"prevClose":600,"diff":5},"numTrans":861,"tradedShares":315251,"amount":190379576},"2024-06-04":{"price":{"open":583.1,"max":631.1,"min":583.1,"close":600,"prevClose":595,"diff":5},"numTrans":657,"tradedShares":197852,"amount":118268633},"2024-06-03":{"price":{"open":571,"max":615,"min":571,"close":595,"prevClose":582,"diff":13},"numTrans":787,"tradedShares":252838,"amount":148595248.2},"2024-06-02":{"price":{"open":581,"max":590,"min":568,"close":582,"prevClose":580,"diff":2},"numTrans":574,"tradedShares":185410,"amount":107130733.3},"2024-05-30":{"price":{"open":575,"max":588.5,"min":565,"close":580,"prevClose":577,"diff":3},"numTrans":556,"tradedShares":181206,"amount":104869522},"2024-05-29":{"price":{"open":584,"max":594,"min":572.1,"close":577,"prevClose":572.8,"diff":4.2000000000000455},"numTrans":734,"tradedShares":176324,"amount":102880823.2},"2024-05-27":{"price":{"open":541,"max":585,"min":541,"close":572.8,"prevClose":552,"diff":20.799999999999955},"numTrans":1248,"tradedShares":355895,"amount":204047434},"2024-05-26":{"price":{"open":561,"max":561,"min":540,"close":552,"prevClose":550,"diff":2},"numTrans":350,"tradedShares":95677,"amount":52501846},"2024-05-22":{"price":{"open":550,"max":561.2,"min":541.1,"close":550,"prevClose":555,"diff":-5},"numTrans":322,"tradedShares":80296,"amount":44245974.1},"2024-05-21":{"price":{"open":528,"max":568,"min":526,"close":555,"prevClose":526,"diff":29},"numTrans":644,"tradedShares":133041,"amount":73471416.3},"2024-05-20":{"price":{"open":531.1,"max":561,"min":520,"close":526,"prevClose":529,"diff":-3},"numTrans":325,"tradedShares":61809,"amount":32849722.6},"2024-05-19":{"price":{"open":505.9,"max":545.6,"min":496,"close":529,"prevClose":496,"diff":33},"numTrans":609,"tradedShares":129566,"amount":68291075},"2024-05-16":{"price":{"open":500,"max":506,"min":494.1,"close":496,"prevClose":500,"diff":-4},"numTrans":154,"tradedShares":24298,"amount":12105167.9},"2024-05-15":{"price":{"open":506,"max":513,"min":500,"close":500,"prevClose":505.5,"diff":-5.5},"numTrans":152,"tradedShares":22095,"amount":11152815.6},"2024-05-14":{"price":{"open":506,"max":514.9,"min":501,"close":505.5,"prevClose":504.9,"diff":0.6000000000000227},"numTrans":168,"tradedShares":25101,"amount":12769686.8},"2024-05-13":{"price":{"open":481.1,"max":521,"min":481.1,"close":504.9,"prevClose":486,"diff":18.899999999999977},"numTrans":207,"tradedShares":39967,"amount":20018368.3},"2024-05-12":{"price":{"open":496.7,"max":496.7,"min":482,"close":486,"prevClose":487.2,"diff":-1.1999999999999886},"numTrans":100,"tradedShares":19508,"amount":9535861.9},"2024-05-09":{"price":{"open":490,"max":496,"min":483,"close":487.2,"prevClose":490,"diff":-2.8000000000000114},"numTrans":115,"tradedShares":11269,"amount":5510862.4},"2024-05-08":{"price":{"open":490,"max":498.9,"min":478.3,"close":490,"prevClose":486.6,"diff":3.3999999999999773},"numTrans":135,"tradedShares":23350,"amount":11325826.5},"2024-05-07":{"price":{"open":498.1,"max":498.1,"min":486.6,"close":486.6,"prevClose":491,"diff":-4.399999999999977},"numTrans":96,"tradedShares":18535,"amount":9102458.2},"2024-05-06":{"price":{"open":492.4,"max":507,"min":490,"close":491,"prevClose":500,"diff":-9},"numTrans":139,"tradedShares":28719,"amount":14121560.3},"2024-05-05":{"price":{"open":515,"max":515,"min":494,"close":500,"prevClose":509,"diff":-9},"numTrans":142,"tradedShares":24085,"amount":12068355},"2024-05-02":{"price":{"open":513,"max":520,"min":507,"close":509,"prevClose":514,"diff":-5},"numTrans":174,"tradedShares":24388,"amount":12526942.4},"2024-04-30":{"price":{"open":500,"max":526.9,"min":495,"close":514,"prevClose":500,"diff":14},"numTrans":281,"tradedShares":72213,"amount":36963716.6},"2024-04-29":{"price":{"open":512.1,"max":515,"min":496,"close":500,"prevClose":512,"diff":-12},"numTrans":147,"tradedShares":17790,"amount":8967081.4},"2024-04-28":{"price":{"open":499,"max":517,"min":495,"close":512,"prevClose":498.2,"diff":13.800000000000011},"numTrans":161,"tradedShares":26694,"amount":13523667},"2024-04-25":{"price":{"open":515,"max":522,"min":498,"close":498.2,"prevClose":525,"diff":-26.80000000000001},"numTrans":186,"tradedShares":30303,"amount":15225175.7},"2024-04-24":{"price":{"open":498,"max":525,"min":489,"close":525,"prevClose":497.5,"diff":27.5},"numTrans":205,"tradedShares":37075,"amount":18358360.2},"2024-04-22":{"price":{"open":507,"max":512,"min":497.2,"close":497.5,"prevClose":507,"diff":-9.5},"numTrans":211,"tradedShares":37697,"amount":19042877.9},"2024-04-21":{"price":{"open":504,"max":511,"min":495,"close":507,"prevClose":511,"diff":-4},"numTrans":192,"tradedShares":30557,"amount":15435323.4},"2024-04-18":{"price":{"open":514.4,"max":524.8,"min":507,"close":511,"prevClose":515.5,"diff":-4.5},"numTrans":134,"tradedShares":13377,"amount":6809629.2},"2024-04-16":{"price":{"open":525.8,"max":526.5,"min":515.5,"close":515.5,"prevClose":530,"diff":-14.5},"numTrans":140,"tradedShares":23699,"amount":12328214.1},"2024-04-15":{"price":{"open":517,"max":545,"min":517,"close":530,"prevClose":518,"diff":12},"numTrans":376,"tradedShares":71642,"amount":38117100},"2024-04-14":{"price":{"open":517.1,"max":524,"min":515.3,"close":518,"prevClose":516.5,"diff":1.5},"numTrans":157,"tradedShares":21812,"amount":11320370.9},"2024-04-10":{"price":{"open":521,"max":525,"min":516,"close":516.5,"prevClose":519,"diff":-2.5},"numTrans":147,"tradedShares":24765,"amount":12860065.8},"2024-04-09":{"price":{"open":531,"max":533,"min":517,"close":519,"prevClose":525,"diff":-6},"numTrans":208,"tradedShares":36534,"amount":19117653.8},"2024-04-07":{"price":{"open":515,"max":525,"min":515,"close":525,"prevClose":515,"diff":10},"numTrans":182,"tradedShares":25490,"amount":13315889.6},"2024-04-04":{"price":{"open":515,"max":523,"min":515,"close":515,"prevClose":524,"diff":-9},"numTrans":187,"tradedShares":28304,"amount":14679413.4},"2024-04-03":{"price":{"open":516.5,"max":540,"min":514,"close":524,"prevClose":516,"diff":8},"numTrans":177,"tradedShares":23595,"amount":12340146.5},"2024-04-02":{"price":{"open":523,"max":529,"min":515,"close":516,"prevClose":522.8,"diff":-6.7999999999999545},"numTrans":159,"tradedShares":20653,"amount":10742228.6},"2024-04-01":{"price":{"open":536,"max":536,"min":519.4,"close":522.8,"prevClose":526,"diff":-3.2000000000000455},"numTrans":210,"tradedShares":27888,"amount":14628228.1},"2024-03-31":{"price":{"open":530,"max":539,"min":525,"close":526,"prevClose":537.9,"diff":-11.899999999999977},"numTrans":202,"tradedShares":29421,"amount":15628719.8},"2024-03-28":{"price":{"open":526.3,"max":540.6,"min":526.3,"close":537.9,"prevClose":530,"diff":7.899999999999977},"numTrans":191,"tradedShares":24653,"amount":13152091.9},"2024-03-27":{"price":{"open":530,"max":540,"min":527.2,"close":530,"prevClose":530.1,"diff":-0.10000000000002274},"numTrans":182,"tradedShares":27926,"amount":14837308.9},"2024-03-26":{"price":{"open":540,"max":541,"min":530.1,"close":530.1,"prevClose":535,"diff":-4.899999999999977},"numTrans":148,"tradedShares":19739,"amount":10576673.6},"2024-03-25":{"price":{"open":536.9,"max":540,"min":533,"close":535,"prevClose":537.2,"diff":-2.2000000000000455},"numTrans":132,"tradedShares":27366,"amount":14650196.9},"2024-03-21":{"price":{"open":554,"max":554,"min":537,"close":537.2,"prevClose":546,"diff":-8.799999999999955},"numTrans":244,"tradedShares":42044,"amount":22853659.4},"2024-03-20":{"price":{"open":561.9,"max":561.9,"min":545.1,"close":546,"prevClose":553,"diff":-7},"numTrans":237,"tradedShares":40087,"amount":22051153.5},"2024-03-19":{"price":{"open":555.1,"max":566,"min":550.1,"close":553,"prevClose":557.9,"diff":-4.899999999999977},"numTrans":227,"tradedShares":49624,"amount":27675106.6},"2024-03-18":{"price":{"open":561,"max":565,"min":553,"close":557.9,"prevClose":557.1,"diff":0.7999999999999545},"numTrans":256,"tradedShares":51871,"amount":28990241.2},"2024-03-17":{"price":{"open":560,"max":566,"min":555,"close":557.1,"prevClose":564,"diff":-6.899999999999977},"numTrans":303,"tradedShares":75138,"amount":42016155.4},"2024-03-14":{"price":{"open":567.6,"max":577,"min":561.2,"close":564,"prevClose":576,"diff":-12},"numTrans":356,"tradedShares":87741,"amount":49761407.6},"2024-03-13":{"price":{"open":595.6,"max":595.6,"min":570,"close":576,"prevClose":584,"diff":-8},"numTrans":403,"tradedShares":73280,"amount":42425297.6},"2024-03-12":{"price":{"open":574.9,"max":588,"min":555.2,"close":584,"prevClose":564,"diff":20},"numTrans":547,"tradedShares":172711,"amount":99155365.7},"2024-03-10":{"price":{"open":563,"max":574,"min":560,"close":564,"prevClose":560,"diff":4},"numTrans":328,"tradedShares":72178,"amount":40962150.8},"2024-03-07":{"price":{"open":564,"max":575,"min":554,"close":560,"prevClose":554,"diff":6},"numTrans":319,"tradedShares":78569,"amount":44126536.5},"2024-03-06":{"price":{"open":549.9,"max":570,"min":530,"close":554,"prevClose":540.1,"diff":13.899999999999977},"numTrans":560,"tradedShares":140217,"amount":77199751.5},"2024-03-05":{"price":{"open":555.7,"max":570,"min":540,"close":540.1,"prevClose":567,"diff":-26.899999999999977},"numTrans":518,"tradedShares":138682,"amount":76973997.6},"2024-03-04":{"price":{"open":527.4,"max":568,"min":527.4,"close":567,"prevClose":517.1,"diff":49.89999999999998},"numTrans":54,"tradedShares":17906,"amount":10053881},"2024-03-03":{"price":{"open":520,"max":530,"min":510,"close":517.1,"prevClose":521.1,"diff":-4},"numTrans":323,"tradedShares":58651,"amount":30372033.2},"2024-02-29":{"price":{"open":540,"max":546.9,"min":520,"close":521.1,"prevClose":540,"diff":-18.899999999999977},"numTrans":315,"tradedShares":89571,"amount":47565379.5},"2024-02-28":{"price":{"open":541.5,"max":557,"min":540,"close":540,"prevClose":547,"diff":-7},"numTrans":221,"tradedShares":49585,"amount":27077942.9},"2024-02-27":{"price":{"open":549,"max":558.5,"min":543,"close":547,"prevClose":550.1,"diff":-3.1000000000000227},"numTrans":187,"tradedShares":39407,"amount":21700877},"2024-02-26":{"price":{"open":535,"max":554.9,"min":535,"close":550.1,"prevClose":540.1,"diff":10},"numTrans":350,"tradedShares":71260,"amount":38838547.2},"2024-02-25":{"price":{"open":562,"max":565,"min":540,"close":540.1,"prevClose":561.9,"diff":-21.799999999999955},"numTrans":385,"tradedShares":79361,"amount":43637895},"2024-02-22":{"price":{"open":585,"max":585,"min":560,"close":561.9,"prevClose":583.4,"diff":-21.5},"numTrans":406,"tradedShares":84830,"amount":48222577},"2024-02-21":{"price":{"open":578,"max":629.8,"min":577.1,"close":583.4,"prevClose":582,"diff":1.3999999999999773},"numTrans":292,"tradedShares":70193,"amount":40920889.3},"2024-02-20":{"price":{"open":582.5,"max":589,"min":574,"close":582,"prevClose":582.5,"diff":-0.5},"numTrans":441,"tradedShares":71086,"amount":41368558.3},"2024-02-18":{"price":{"open":599.9,"max":599.9,"min":582.5,"close":582.5,"prevClose":593,"diff":-10.5},"numTrans":435,"tradedShares":116232,"amount":68229377.5},"2024-02-15":{"price":{"open":598,"max":610,"min":593,"close":593,"prevClose":605,"diff":-12},"numTrans":453,"tradedShares":96390,"amount":58031956.2},"2024-02-14":{"price":{"open":599,"max":610,"min":591,"close":605,"prevClose":596.3,"diff":8.700000000000045},"numTrans":420,"tradedShares":105282,"amount":63348108.8},"2024-07-16":{"price":{"open":748,"max":800.7,"min":748,"close":800.7,"prevClose":748,"diff":52.700000000000045},"numTrans":1051,"tradedShares":234237,"amount":182748795.8},"2024-07-15":{"price":{"open":758,"max":773.2,"min":746.2,"close":748,"prevClose":758,"diff":-10},"numTrans":841,"tradedShares":216585,"amount":164286301.7},"2024-07-14":{"price":{"open":745,"max":774,"min":730.1,"close":758,"prevClose":730.4,"diff":27.600000000000023},"numTrans":1125,"tradedShares":282174,"amount":212747749.3},"2024-07-11":{"price":{"open":729,"max":742.9,"min":726,"close":730.4,"prevClose":729,"diff":1.3999999999999773},"numTrans":710,"tradedShares":161341,"amount":117938710.6},"2024-07-10":{"price":{"open":739,"max":744,"min":723.1,"close":729,"prevClose":735,"diff":-6},"numTrans":690,"tradedShares":156196,"amount":113939052.7},"2024-07-09":{"price":{"open":730,"max":779,"min":723,"close":735,"prevClose":724,"diff":11},"numTrans":918,"tradedShares":270154,"amount":197775931.1},"2024-07-08":{"price":{"open":730,"max":765,"min":721,"close":724,"prevClose":742,"diff":-18},"numTrans":1144,"tradedShares":390205,"amount":287080935.8},"2024-07-07":{"price":{"open":700,"max":750,"min":700,"close":742,"prevClose":708,"diff":34},"numTrans":1527,"tradedShares":295259,"amount":217148801.1},"2024-07-04":{"price":{"open":674,"max":717.9,"min":670,"close":708,"prevClose":670,"diff":38},"numTrans":1781,"tradedShares":428836,"amount":300904694},"2024-07-03":{"price":{"open":675,"max":679.5,"min":665,"close":670,"prevClose":680.5,"diff":-10.5},"numTrans":380,"tradedShares":79018,"amount":53041024.8},"2024-07-02":{"price":{"open":669.4,"max":705,"min":669.4,"close":680.5,"prevClose":656.3,"diff":24.200000000000045},"numTrans":644,"tradedShares":181060,"amount":123385569.2},"2024-07-01":{"price":{"open":652.1,"max":667.9,"min":640.1,"close":656.3,"prevClose":650,"diff":6.2999999999999545},"numTrans":451,"tradedShares":179545,"amount":118574401.9},"2024-06-30":{"price":{"open":650.8,"max":674.9,"min":647,"close":650,"prevClose":664,"diff":-14},"numTrans":408,"tradedShares":135110,"amount":89445796},"2024-06-27":{"price":{"open":666.4,"max":680,"min":660.1,"close":664,"prevClose":680,"diff":-16},"numTrans":486,"tradedShares":98614,"amount":65963124.6},"2024-06-26":{"price":{"open":670,"max":706.8,"min":670,"close":680,"prevClose":682.9,"diff":-2.8999999999999773},"numTrans":706,"tradedShares":195097,"amount":133354017.6},"2024-06-25":{"price":{"open":649,"max":697,"min":649,"close":682.9,"prevClose":662,"diff":20.899999999999977},"numTrans":895,"tradedShares":185330,"amount":126231466.7},"2024-06-24":{"price":{"open":643.9,"max":677,"min":643.9,"close":662,"prevClose":657,"diff":5},"numTrans":932,"tradedShares":276143,"amount":184153991.8},"2024-06-23":{"price":{"open":644.9,"max":677,"min":644.9,"close":657,"prevClose":658,"diff":-1},"numTrans":741,"tradedShares":144677,"amount":96155098},"2024-06-20":{"price":{"open":622.3,"max":667,"min":622.3,"close":658,"prevClose":635,"diff":23},"numTrans":976,"tradedShares":242053,"amount":157489742.4},"2024-06-19":{"price":{"open":616.5,"max":644,"min":616.5,"close":635,"prevClose":629,"diff":6},"numTrans":464,"tradedShares":108380,"amount":68645528.4},"2024-06-18":{"price":{"open":640.1,"max":653,"min":629,"close":629,"prevClose":646,"diff":-17},"numTrans":623,"tradedShares":161752,"amount":103755496.6},"2024-06-13":{"price":{"open":680.2,"max":692,"min":640,"close":640,"prevClose":694,"diff":-54},"numTrans":1554,"tradedShares":313127,"amount":205758177.3},"2024-06-12":{"price":{"open":706.6,"max":778,"min":678,"close":694,"prevClose":721,"diff":-27},"numTrans":1632,"tradedShares":396134,"amount":276360491.5}}